pyvrp/IteratedLocalSearch.py
pyvrp/Model.py
pyvrp/PenaltyManager.py
pyvrp/ProgressPrinter.py
pyvrp/Result.py
pyvrp/RingBuffer.py
pyvrp/Statistics.py
pyvrp/__init__.py
pyvrp/_pyvrp.cpython-311-x86_64-linux-musl.so
pyvrp/_pyvrp.pyi
pyvrp/cli.py
pyvrp/constants.py
pyvrp/exceptions.py
pyvrp/minimise_fleet.py
pyvrp/py.typed
pyvrp/read.py
pyvrp/show_versions.py
pyvrp/solve.py
pyvrp/cpp/CostEvaluator.cpp
pyvrp/cpp/CostEvaluator.h
pyvrp/cpp/DurationSegment.cpp
pyvrp/cpp/DurationSegment.h
pyvrp/cpp/DynamicBitset.cpp
pyvrp/cpp/DynamicBitset.h
pyvrp/cpp/LoadSegment.cpp
pyvrp/cpp/LoadSegment.h
pyvrp/cpp/Matrix.h
pyvrp/cpp/Measure.h
pyvrp/cpp/ProblemData.cpp
pyvrp/cpp/ProblemData.h
pyvrp/cpp/README.md
pyvrp/cpp/RandomNumberGenerator.cpp
pyvrp/cpp/RandomNumberGenerator.h
pyvrp/cpp/Route.cpp
pyvrp/cpp/Route.h
pyvrp/cpp/Solution.cpp
pyvrp/cpp/Solution.h
pyvrp/cpp/Trip.cpp
pyvrp/cpp/Trip.h
pyvrp/cpp/bindings.cpp
pyvrp/cpp/bindings.h
pyvrp/cpp/search/Exchange.h
pyvrp/cpp/search/LocalSearch.cpp
pyvrp/cpp/search/LocalSearch.h
pyvrp/cpp/search/LocalSearchOperator.h
pyvrp/cpp/search/PerturbationManager.cpp
pyvrp/cpp/search/PerturbationManager.h
pyvrp/cpp/search/RelocateWithDepot.cpp
pyvrp/cpp/search/RelocateWithDepot.h
pyvrp/cpp/search/Route.cpp
pyvrp/cpp/search/Route.h
pyvrp/cpp/search/SearchSpace.cpp
pyvrp/cpp/search/SearchSpace.h
pyvrp/cpp/search/Solution.cpp
pyvrp/cpp/search/Solution.h
pyvrp/cpp/search/SwapRoutes.cpp
pyvrp/cpp/search/SwapRoutes.h
pyvrp/cpp/search/SwapStar.cpp
pyvrp/cpp/search/SwapStar.h
pyvrp/cpp/search/SwapTails.cpp
pyvrp/cpp/search/SwapTails.h
pyvrp/cpp/search/bindings.cpp
pyvrp/cpp/search/primitives.cpp
pyvrp/cpp/search/primitives.h
pyvrp/plotting/__init__.py
pyvrp/plotting/plot_coordinates.py
pyvrp/plotting/plot_demands.py
pyvrp/plotting/plot_instance.py
pyvrp/plotting/plot_objectives.py
pyvrp/plotting/plot_result.py
pyvrp/plotting/plot_route_schedule.py
pyvrp/plotting/plot_runtimes.py
pyvrp-0.13.2.dist-info/METADATA
pyvrp-0.13.2.dist-info/WHEEL
pyvrp-0.13.2.dist-info/entry_points.txt
pyvrp-0.13.2.dist-info/RECORD
pyvrp-0.13.2.dist-info/licenses/LICENSE.md
