Metadata-Version: 2.4
Name: pyvrp
Version: 0.13.2
Summary: A state-of-the-art vehicle routing problem solver.
License-Expression: MIT
License-File: LICENSE.md
Keywords: vehicle routing problem,vrp,metaheuristic,logistics,optimization,optimisation
Author: Niels Wouda
Author-email: nielswouda@gmail.com
Requires-Python: >=3.11
Classifier: Intended Audience :: Developers
Classifier: Intended Audience :: Science/Research
Classifier: Development Status :: 5 - Production/Stable
Classifier: Topic :: Software Development
Classifier: Topic :: Scientific/Engineering
Classifier: Programming Language :: Python :: 3
Classifier: Programming Language :: Python :: 3.11
Classifier: Programming Language :: Python :: 3.12
Classifier: Programming Language :: Python :: 3.13
Classifier: Programming Language :: Python :: 3.14
Requires-Dist: matplotlib (>=2.2.0)
Requires-Dist: numpy (>=1.15.2) ; python_version < "3.12"
Requires-Dist: numpy (>=1.26.0) ; python_version >= "3.12"
Requires-Dist: tqdm (>=4.64.1)
Requires-Dist: vrplib (>=1.4.0)
Project-URL: Documentation, https://pyvrp.org/
Project-URL: Homepage, https://pyvrp.org/
Project-URL: issues, https://github.com/PyVRP/PyVRP/issues
Project-URL: source, https://github.com/PyVRP/PyVRP
